ChangeLog.rst
LICENSE
MANIFEST.in
README.rst
setup.py
deep_collector/__init__.py
deep_collector/core.py
deep_collector/utils.py
deep_collector/compat/__init__.py
deep_collector/compat/builtins.py
deep_collector/compat/fields.py
deep_collector/compat/meta.py
deep_collector/compat/serializers/__init__.py
deep_collector/compat/serializers/django_1_6.py
deep_collector/compat/serializers/django_1_7.py
deep_collector/compat/serializers/django_1_9.py
django_deep_collector.egg-info/PKG-INFO
django_deep_collector.egg-info/SOURCES.txt
django_deep_collector.egg-info/dependency_links.txt
django_deep_collector.egg-info/top_level.txt